kca/__init__.py
kca/activations/__init__.py
kca/activations/glu.py
kca/activations/sparsemax.py
kca/layers/__init__.py
kca/layers/convmixer/__init__.py
kca/layers/fnet/__init__.py
kca/layers/gmlp/__init__.py
kca/layers/mlpmixer/__init__.py
kca/layers/ndf/__init__.py
kca/layers/residual.py
kca/layers/stochastic_depth.py
kca/layers/tabnet/__init__.py
kca/layers/tft/__init__.py
kca/layers/transformer/__init__.py
kca/layers/transformer/block.py
kca/losses/__init__.py
kca/losses/ntxent.py
kca/utils/__init__.py
kca/utils/types.py
kca-0.3.dev0.dist-info/LICENSE
kca-0.3.dev0.dist-info/METADATA
kca-0.3.dev0.dist-info/WHEEL
kca-0.3.dev0.dist-info/RECORD
