Metadata-Version: 2.1
Name: kca
Version: 0.3.dev0
Summary: Keras Core Addons: Useful extra functionality for Keras Core.
Home-page: https://github.com/terminalai/kca
License: MIT
Keywords: keras,keras-core,addons,machine,learning
Author: Prannaya Gupta
Author-email: prannayagupta@programmer.net
Requires-Python: >=3.8
Classifier: Development Status :: 4 - Beta
Classifier: Intended Audience :: Science/Research
Classifier: License :: OSI Approved :: MIT License
Classifier: Operating System :: MacOS
Classifier: Operating System :: Unix
Classifier: Programming Language :: Python :: 3
Classifier: Programming Language :: Python :: 3.8
Classifier: Programming Language :: Python :: 3.9
Classifier: Programming Language :: Python :: 3.10
Classifier: Programming Language :: Python :: 3.11
Classifier: Topic :: Scientific/Engineering
Classifier: Topic :: Software Development
Requires-Dist: keras-core (>=0.1.15,<0.2.0)
Requires-Dist: numpy (<=1.24)
Requires-Dist: tensorflow (>=2.12.0,<2.13.0)
Project-URL: Bug Tracker, https://github.com/terminalai/kca/issues
Project-URL: Documentation, https://github.com/terminalai/kca
Project-URL: Repository, https://github.com/terminalai/kca
